monapipe/__init__.py
monapipe/annotation.py
monapipe/config.py
monapipe/docker.py
monapipe/linguistics.py
monapipe/lookups.py
monapipe/model.py
monapipe/neuralcoref.py
monapipe/pickling.py
monapipe/resource_handler.py
monapipe/silence.py
monapipe/lang/__init__.py
monapipe/lang/de/__init__.py
monapipe/lang/de/auxiliary_verbs.py
monapipe/lang/de/inflection_table.py
monapipe/lang/de/modal_verbs.py
monapipe/lang/de/quotation_marks.py
monapipe/lang/de/semi_modal_verbs.py
monapipe/lang/de/speech_verbs.py
monapipe/pipeline/__init__.py
monapipe/pipeline/methods.py
monapipe/pipeline/annotation_reader/__init__.py
monapipe/pipeline/annotation_reader/annotation_reader.py
monapipe/pipeline/annotation_reader/catma_annotation_reader.py
monapipe/pipeline/attribution_tagger/__init__.py
monapipe/pipeline/attribution_tagger/attribution_tagger.py
monapipe/pipeline/attribution_tagger/neural_attribution_tagger.py
monapipe/pipeline/attribution_tagger/neural_attribution_tagger_api/Dockerfile
monapipe/pipeline/attribution_tagger/neural_attribution_tagger_api/__init__.py
monapipe/pipeline/attribution_tagger/neural_attribution_tagger_api/requirements.txt
monapipe/pipeline/attribution_tagger/neural_attribution_tagger_api/app/__init__.py
monapipe/pipeline/attribution_tagger/neural_attribution_tagger_api/app/main.py
monapipe/pipeline/attribution_tagger/neural_attribution_tagger_api/app/request_neural_attribution_tagger.py
monapipe/pipeline/attribution_tagger/neural_attribution_tagger_api/app/data/__init__.py
monapipe/pipeline/attribution_tagger/neural_attribution_tagger_api/app/resources/__init__.py
monapipe/pipeline/attribution_tagger/neural_attribution_tagger_api/app/resources/_dbmdz_bert_base_german_cased/__init__.py
monapipe/pipeline/attribution_tagger/neural_attribution_tagger_api/app/resources/_dbmdz_bert_base_german_cased/load.py
monapipe/pipeline/attribution_tagger/neural_attribution_tagger_api/app/resources/neural_attribution_tagger/__init__.py
monapipe-4.9.1.dist-info/licenses/LICENSES/CC-BY 4.0.txt
monapipe-4.9.1.dist-info/licenses/LICENSES/CC-BY-NC-SA 4.0.txt
monapipe-4.9.1.dist-info/licenses/LICENSES/CC-BY-SA 3.0.txt
monapipe-4.9.1.dist-info/licenses/LICENSES/CC-BY-SA 4.0.txt
monapipe-4.9.1.dist-info/licenses/LICENSES/CC0-1.0.txt
monapipe-4.9.1.dist-info/licenses/LICENSES/FDL-1.1.txt
monapipe-4.9.1.dist-info/licenses/LICENSES/GPL-3.0.txt
monapipe-4.9.1.dist-info/licenses/LICENSES/LGPL-3.0-or-later.txt
monapipe-4.9.1.dist-info/licenses/LICENSES/MIT.txt
monapipe-4.9.1.dist-info/licenses/LICENSES/bsd-2-clause.txt
monapipe-4.9.1.dist-info/licenses/LICENSES/open_multilingual_wordnet_license_statement.txt
monapipe-4.9.1.dist-info/METADATA
monapipe-4.9.1.dist-info/WHEEL
monapipe-4.9.1.dist-info/top_level.txt
monapipe-4.9.1.dist-info/RECORD
