Metadata-Version: 2.4
Name: monapipe
Version: 4.9.1
Summary: MONAPipe provides natural-language-processing tools for German, implemented in Python/spaCy.
Author: Tillmann Dönicke, Florian Barth, Hanna Varachkina
Maintainer-email: Florian Barth <florian.barth@uni-goettingen.de>
License: GNU LESSER GENERAL PUBLIC LICENSE
Project-URL: Documentation, https://textplus.pages.gwdg.de/collections/mona-pipe/
Project-URL: Source, https://gitlab.gwdg.de/textplus/collections/mona-pipe
Classifier: Programming Language :: Python :: 3
Classifier: Programming Language :: Python :: 3.9
Classifier: Programming Language :: Python :: 3.10
Classifier: Programming Language :: Python :: 3.11
Classifier: Programming Language :: Python :: 3.12
Classifier: License :: OSI Approved :: GNU Lesser General Public License v3 (LGPLv3)
Classifier: License :: CC0 1.0 Universal (CC0 1.0) Public Domain Dedication
Classifier: Operating System :: OS Independent
Requires-Python: <3.13,>=3.9
License-File: LICENSES/CC-BY 4.0.txt
License-File: LICENSES/CC-BY-NC-SA 4.0.txt
License-File: LICENSES/CC-BY-SA 3.0.txt
License-File: LICENSES/CC-BY-SA 4.0.txt
License-File: LICENSES/CC0-1.0.txt
License-File: LICENSES/FDL-1.1.txt
License-File: LICENSES/GPL-3.0.txt
License-File: LICENSES/LGPL-3.0-or-later.txt
License-File: LICENSES/MIT.txt
License-File: LICENSES/bsd-2-clause.txt
License-File: LICENSES/open_multilingual_wordnet_license_statement.txt
Requires-Dist: pip>=23.2.2
Requires-Dist: setuptools>=69.0.3
Requires-Dist: wheel>=0.42.0
Requires-Dist: dill
Requires-Dist: docker
Requires-Dist: germanetpy
Requires-Dist: ipykernel
Requires-Dist: more_itertools
Requires-Dist: nltk
Requires-Dist: omegaconf
Requires-Dist: pytorch_transformers
Requires-Dist: scipy
Requires-Dist: spacy>=3.0
Requires-Dist: spacy-alignments
Requires-Dist: spacy-dbpedia-spotlight
Requires-Dist: spacy_download
Requires-Dist: spacy-curated-transformers
Requires-Dist: spacyopentapioca
Requires-Dist: spacyfishing
Requires-Dist: tgclients
Requires-Dist: langchain
Requires-Dist: langchain_openai
Dynamic: license-file
